streamlit_datalist/__init__.py
streamlit_datalist/frontend/build/asset-manifest.json
streamlit_datalist/frontend/build/bootstrap.min.css
streamlit_datalist/frontend/build/index.html
streamlit_datalist/frontend/build/precache-manifest.315dace4a9cc8b0b86a6e26a95ace93c.js
streamlit_datalist/frontend/build/precache-manifest.b6b025c5479c67524b3ceb6dc4cd27c9.js
streamlit_datalist/frontend/build/service-worker.js
streamlit_datalist/frontend/build/static/js/2.2cdf07e4.chunk.js
streamlit_datalist/frontend/build/static/js/2.2cdf07e4.chunk.js.LICENSE.txt
streamlit_datalist/frontend/build/static/js/2.2cdf07e4.chunk.js.map
streamlit_datalist/frontend/build/static/js/2.96dc815c.chunk.js
streamlit_datalist/frontend/build/static/js/2.96dc815c.chunk.js.LICENSE.txt
streamlit_datalist/frontend/build/static/js/2.96dc815c.chunk.js.map
streamlit_datalist/frontend/build/static/js/main.b5ef2d84.chunk.js
streamlit_datalist/frontend/build/static/js/main.b5ef2d84.chunk.js.map
streamlit_datalist/frontend/build/static/js/main.f77b83ac.chunk.js
streamlit_datalist/frontend/build/static/js/main.f77b83ac.chunk.js.map
streamlit_datalist/frontend/build/static/js/runtime-main.5ae4fbea.js
streamlit_datalist/frontend/build/static/js/runtime-main.5ae4fbea.js.map
streamlit_datalist-0.0.5.dist-info/LICENSE
streamlit_datalist-0.0.5.dist-info/METADATA
streamlit_datalist-0.0.5.dist-info/WHEEL
streamlit_datalist-0.0.5.dist-info/top_level.txt
streamlit_datalist-0.0.5.dist-info/RECORD
