Metadata-Version: 2.1
Name: streamlit-datalist
Version: 0.0.5
Summary: Datalist element for Streamlit
Home-page: https://github.com/RobertoFN/streamlit-datalist
Author: Roberto Frias Nerio
Author-email: robertofnerio@gmail.com
License: UNKNOWN
Platform: UNKNOWN
Requires-Python: >=3.6
Requires-Dist: streamlit (>=0.63)
